{"BG": {"IR": 0.0, "ET": 0.0, "IT": 0.0, "CZ": 0.0, "PR": 0.0, "LV": 0.0, "UI": 0.0, "FN": 336699605.0, "ES": 0.0, "EE": 0.0, "UK": 0.0, "DU": 0.0, "FR": 0.0, "SI": 0.0, "IE": 0.0, "BE": 930139.0, "LN": 0.0, "AT": 0.0, "PL": 0.0, "DE": 506345467.0, "SK": 0.0, "NL": 0.0, "LT": 0.0, "HU": 0.0, "CH": 0.0, "HR": 0.0, "GC": 0.0, "PT": 0.0, "RO": 0.0, "GR": 0.0}, "IR": {"BG": 0.0, "ET": 0.0, "IT": 0.0, "CZ": 110888572.0, "PR": 0.0, "LV": 0.0, "UI": 0.0, "FN": 0.0, "ES": 0.0, "EE": 77586758.0, "UK": 0.0, "DU": 0.0, "FR": 0.0, "SI": 0.0, "IE": 0.0, "BE": 0.0, "LN": 0.0, "AT": 0.0, "PL": 0.0, "DE": 0.0, "SK": 0.0, "NL": 0.0, "LT": 0.0, "HU": 0.0, "CH": 0.0, "HR": 0.0, "GC": 0.0, "PT": 31525345.0, "RO": 0.0, "GR": 0.0}, "ET": {"LT": 1673268.0, "BG": 0.0, "IR": 0.0, "HR": 791626.0, "CZ": 0.0, "PR": 0.0, "LV": 92226622.0, "UI": 0.0, "FN": 0.0, "ES": 0.0, "EE": 0.0, "UK": 0.0, "DU": 0.0, "FR": 0.0, "SI": 0.0, "IE": 0.0, "BE": 14824.0, "LN": 0.0, "AT": 0.0, "PL": 0.0, "DE": 0.0, "SK": 0.0, "NL": 0.0, "IT": 0.0, "HU": 0.0, "CH": 28711620.0, "GC": 0.0, "PT": 0.0, "RO": 0.0, "GR": 0.0}, "IT": {"LT": 0.0, "BG": 0.0, "IR": 0.0, "HR": 0.0, "CZ": 0.0, "PR": 0.0, "LV": 0.0, "UI": 0.0, "FN": 0.0, "ES": 0.0, "EE": 0.0, "UK": 19698710871.0, "DU": 0.0, "FR": 0.0, "SI": 0.0, "IE": 0.0, "BE": 0.0, "LN": 0.0, "AT": 0.0, "PL": 0.0, "DE": 0.0, "SK": 0.0, "NL": 0.0, "ET": 0.0, "HU": 0.0, "CH": 0.0, "GC": 0.0, "PT": 0.0, "RO": 0.0, "GR": 0.0}, "CZ": {"BG": 0.0, "IR": 0.0, "ET": 0.0, "IT": 0.0, "ES": 9686884.0, "PR": 1353699999.0, "LV": 0.0, "UI": 0.0, "FN": 0.0, "EE": 0.0, "UK": 0.0, "DU": 0.0, "FR": 0.0, "SI": 0.0, "IE": 0.0, "BE": 0.0, "LN": 0.0, "AT": 0.0, "PL": 0.0, "DE": 0.0, "SK": 0.0, "NL": 0.0, "LT": 0.0, "HU": 0.0, "CH": 0.0, "HR": 0.0, "GC": 0.0, "PT": 0.0, "RO": 0.0, "GR": 0.0}, "PR": {"BG": 0.0, "IR": 0.0, "ET": 0.0, "IT": 0.0, "CZ": 1131315306.0, "LV": 0.0, "UI": 0.0, "FN": 0.0, "ES": 0.0, "EE": 0.0, "UK": 369623800.0, "DU": 0.0, "FR": 0.0, "SI": 0.0, "IE": 0.0, "BE": 0.0, "LN": 0.0, "AT": 0.0, "PL": 0.0, "DE": 0.0, "SK": 0.0, "NL": 1005931496.0, "LT": 0.0, "HU": 0.0, "CH": 0.0, "HR": 0.0, "GC": 0.0, "PT": 435640728.0, "RO": 50738941.0, "GR": 0.0}, "LV": {"BG": 0.0, "IR": 0.0, "ET": 27764778.0, "IT": 0.0, "CZ": 0.0, "PR": 0.0, "NL": 0.0, "UI": 0.0, "FN": 0.0, "ES": 0.0, "EE": 26998154.0, "UK": 0.0, "DU": 0.0, "FR": 0.0, "SI": 0.0, "IE": 0.0, "BE": 0.0, "LN": 0.0, "AT": 0.0, "PL": 0.0, "DE": 0.0, "SK": 0.0, "LT": 0.0, "HU": 0.0, "CH": 0.0, "HR": 556947.0, "GC": 0.0, "PT": 0.0, "RO": 0.0, "GR": 0.0}, "UI": {"BG": 0.0, "IR": 0.0, "ET": 5029774.0, "IT": 26816690848.0, "CZ": 17637239426.0, "PR": 0.0, "LV": 0.0, "HR": 0.0, "FN": 0.0, "ES": 0.0, "EE": 2837161948.0, "UK": 0.0, "DU": 9551356700.0, "FR": 0.0, "SI": 0.0, "IE": 0.0, "BE": 0.0, "LN": 0.0, "AT": 0.0, "PL": 0.0, "DE": 0.0, "SK": 0.0, "NL": 39072907631.0, "LT": 0.0, "HU": 0.0, "CH": 0.0, "GC": 0.0, "PT": 0.0, "RO": 0.0, "GR": 0.0}, "FN": {"BG": 0.0, "IR": 0.0, "ET": 0.0, "IT": 822854277.0, "CZ": 794814115.0, "PR": 0.0, "LV": 0.0, "UI": 0.0, "GC": 0.0, "ES": 8161715765.0, "EE": 0.0, "UK": 0.0, "DU": 0.0, "FR": 8248090815.0, "SI": 0.0, "IE": 0.0, "BE": 0.0, "LN": 0.0, "AT": 0.0, "PL": 0.0, "DE": 5150184960.0, "SK": 0.0, "NL": 2335229820.0, "LT": 0.0, "HU": 0.0, "CH": 0.0, "HR": 0.0, "PT": 230722978.0, "RO": 0.0, "GR": 41844120.0}, "ES": {"BG": 0.0, "IR": 0.0, "ET": 0.0, "IT": 2699237203.0, "CZ": 0.0, "PR": 0.0, "LV": 0.0, "UI": 0.0, "FN": 6156401372.0, "EE": 0.0, "UK": 1342809128.0, "DU": 0.0, "FR": 0.0, "SI": 1127931545.0, "IE": 0.0, "BE": 0.0, "LN": 0.0, "AT": 0.0, "PL": 0.0, "DE": 0.0, "SK": 0.0, "NL": 0.0, "LT": 501460097.0, "HU": 3502957859.0, "CH": 0.0, "HR": 872226.0, "GC": 0.0, "PT": 192565771.0, "RO": 0.0, "GR": 0.0}, "EE": {"BG": 238522977.0, "IR": 0.0, "ET": 0.0, "IT": 0.0, "CZ": 0.0, "PR": 0.0, "LV": 115838591.0, "UI": 0.0, "FN": 0.0, "ES": 0.0, "UK": 0.0, "DU": 0.0, "FR": 0.0, "SI": 0.0, "IE": 14964.0, "BE": 0.0, "LN": 2027177.0, "AT": 0.0, "PL": 321399759.0, "DE": 1405557888.0, "SK": 583578500.0, "NL": 0.0, "LT": 0.0, "HU": 0.0, "CH": 0.0, "HR": 0.0, "GC": 0.0, "PT": 0.0, "RO": 1216230115.0, "GR": 0.0}, "UK": {"BG": 0.0, "IR": 1380516.0, "ET": 0.0, "IT": 0.0, "CZ": 0.0, "PR": 0.0, "LV": 0.0, "UI": 80684950515.0, "FN": 0.0, "ES": 0.0, "EE": 0.0, "DU": 0.0, "FR": 0.0, "SI": 0.0, "IE": 0.0, "BE": 0.0, "LN": 0.0, "AT": 0.0, "PL": 0.0, "DE": 3527961214.0, "SK": 0.0, "NL": 0.0, "LT": 0.0, "HU": 2167650203.0, "CH": 0.0, "HR": 0.0, "GC": 0.0, "PT": 0.0, "RO": 0.0, "GR": 0.0}, "DU": {"BG": 0.0, "IR": 0.0, "ET": 93592951.0, "IT": 0.0, "CZ": 3170645008.0, "PR": 0.0, "LV": 0.0, "UI": 0.0, "FN": 0.0, "ES": 0.0, "EE": 1961281222.0, "UK": 0.0, "FR": 19479435268.0, "SI": 0.0, "IE": 0.0, "BE": 0.0, "LN": 0.0, "AT": 0.0, "PL": 0.0, "DE": 0.0, "SK": 0.0, "NL": 0.0, "LT": 0.0, "HU": 0.0, "CH": 0.0, "HR": 0.0, "GC": 3972304946.0, "PT": 0.0, "RO": 2144182638.0, "GR": 0.0}, "FR": {"BG": 0.0, "IR": 0.0, "ET": 0.0, "CZ": 10145987956.0, "PR": 0.0, "LV": 0.0, "UI": 0.0, "FN": 0.0, "ES": 2961862660.0, "EE": 0.0, "UK": 0.0, "DU": 0.0, "IT": 0.0, "SI": 2745952987.0, "IE": 0.0, "BE": 0.0, "LN": 0.0, "AT": 0.0, "PL": 4295738508.0, "DE": 0.0, "SK": 0.0, "NL": 22564297288.0, "LT": 967229868.0, "HU": 0.0, "CH": 0.0, "HR": 0.0, "GC": 0.0, "PT": 0.0, "RO": 1992742356.0, "GR": 0.0}, "SI": {"BG": 0.0, "IR": 0.0, "ET": 0.0, "IT": 0.0, "CZ": 0.0, "PR": 0.0, "LV": 0.0, "UI": 0.0, "FN": 4082351.0, "ES": 7430073862.0, "EE": 0.0, "UK": 0.0, "DU": 0.0, "FR": 0.0, "IE": 0.0, "BE": 0.0, "LN": 0.0, "AT": 0.0, "PL": 0.0, "DE": 0.0, "SK": 0.0, "NL": 11661936901.0, "LT": 0.0, "HU": 3479810461.0, "CH": 0.0, "HR": 0.0, "GC": 0.0, "PT": 0.0, "RO": 0.0, "GR": 0.0}, "IE": {"BG": 0.0, "IR": 0.0, "ET": 0.0, "IT": 0.0, "CZ": 0.0, "PR": 933998.0, "LV": 0.0, "UI": 0.0, "FN": 0.0, "ES": 229880556.0, "EE": 0.0, "UK": 0.0, "DU": 679376459.0, "FR": 0.0, "SI": 0.0, "BE": 0.0, "LN": 0.0, "AT": 0.0, "PL": 0.0, "DE": 0.0, "SK": 0.0, "NL": 0.0, "LT": 552972977.0, "HU": 0.0, "CH": 0.0, "HR": 0.0, "GC": 0.0, "PT": 0.0, "RO": 0.0, "GR": 3224289874.0}, "BE": {"BG": 0.0, "IR": 0.0, "IT": 0.0, "CZ": 0.0, "PR": 0.0, "LV": 0.0, "UI": 0.0, "FN": 0.0, "ES": 0.0, "EE": 0.0, "UK": 0.0, "DU": 0.0, "FR": 0.0, "SI": 0.0, "IE": 0.0, "ET": 0.0, "LN": 315284.0, "AT": 0.0, "PL": 0.0, "DE": 0.0, "SK": 0.0, "NL": 0.0, "LT": 0.0, "HU": 0.0, "CH": 0.0, "HR": 719227.0, "GC": 0.0, "PT": 0.0, "RO": 0.0, "GR": 0.0}, "LN": {"BG": 0.0, "IR": 0.0, "ET": 0.0, "IT": 0.0, "CZ": 0.0, "PR": 0.0, "LV": 0.0, "UI": 0.0, "FN": 0.0, "ES": 6603425.0, "EE": 566883.0, "UK": 0.0, "DU": 0.0, "FR": 0.0, "SI": 0.0, "IE": 0.0, "BE": 0.0, "AT": 0.0, "PL": 0.0, "DE": 0.0, "SK": 0.0, "NL": 0.0, "LT": 0.0, "HU": 0.0, "CH": 0.0, "HR": 0.0, "GC": 0.0, "PT": 0.0, "RO": 0.0, "GR": 0.0}, "AT": {"BG": 0.0, "IR": 0.0, "ET": 0.0, "IT": 0.0, "CZ": 0.0, "PR": 668156824.0, "LV": 0.0, "UI": 0.0, "FN": 0.0, "ES": 0.0, "EE": 0.0, "UK": 0.0, "DU": 0.0, "FR": 0.0, "SI": 0.0, "IE": 0.0, "BE": 0.0, "LN": 0.0, "PL": 0.0, "DE": 0.0, "SK": 901472691.0, "NL": 3076746649.0, "LT": 0.0, "HU": 0.0, "CH": 0.0, "HR": 0.0, "GC": 2257089733.0, "PT": 357325802.0, "RO": 0.0, "GR": 4853242439.0}, "PL": {"BG": 0.0, "IR": 0.0, "ET": 0.0, "IT": 481042037.0, "CZ": 0.0, "PR": 0.0, "LV": 0.0, "UI": 0.0, "FN": 541420022.0, "ES": 0.0, "EE": 0.0, "UK": 0.0, "DU": 0.0, "FR": 1855441406.0, "SI": 0.0, "IE": 0.0, "BE": 0.0, "LN": 0.0, "AT": 0.0, "DE": 0.0, "SK": 0.0, "NL": 3207491600.0, "LT": 0.0, "HU": 0.0, "CH": 0.0, "HR": 0.0, "GC": 0.0, "PT": 0.0, "RO": 0.0, "GR": 0.0}, "DE": {"BG": 0.0, "IR": 0.0, "ET": 0.0, "IT": 42267098318.0, "CZ": 0.0, "PR": 0.0, "LV": 0.0, "UI": 15792761671.0, "FN": 0.0, "ES": 0.0, "EE": 0.0, "UK": 0.0, "DU": 0.0, "FR": 0.0, "SI": 0.0, "IE": 0.0, "BE": 0.0, "LN": 207895.0, "AT": 0.0, "PL": 0.0, "SK": 0.0, "NL": 19813693134.0, "LT": 0.0, "HU": 0.0, "CH": 0.0, "HR": 0.0, "GC": 0.0, "PT": 0.0, "RO": 0.0, "GR": 0.0}, "SK": {"BG": 196159885.0, "IR": 0.0, "ET": 0.0, "IT": 0.0, "CZ": 2527393514.0, "PR": 0.0, "LV": 0.0, "UI": 0.0, "FN": 0.0, "ES": 0.0, "EE": 0.0, "UK": 0.0, "DU": 0.0, "FR": 3325396561.0, "SI": 0.0, "IE": 0.0, "BE": 0.0, "LN": 1105159.0, "AT": 0.0, "PL": 0.0, "DE": 0.0, "HR": 0.0, "NL": 0.0, "LT": 0.0, "HU": 37066800.0, "CH": 0.0, "GC": 0.0, "PT": 0.0, "RO": 0.0, "GR": 494058824.0}, "NL": {"BG": 0.0, "IR": 0.0, "ET": 0.0, "IT": 0.0, "CZ": 0.0, "PR": 0.0, "LV": 0.0, "UI": 0.0, "FN": 4058316486.0, "ES": 1329455805.0, "EE": 4718630672.0, "UK": 0.0, "DU": 0.0, "FR": 22471266776.0, "SI": 0.0, "IE": 304622580.0, "BE": 0.0, "LN": 0.0, "AT": 0.0, "PL": 3387254985.0, "DE": 0.0, "SK": 0.0, "LT": 0.0, "HU": 0.0, "CH": 0.0, "HR": 0.0, "GC": 7010550878.0, "PT": 0.0, "RO": 0.0, "GR": 3503540395.0}, "LT": {"BG": 0.0, "IR": 0.0, "IT": 0.0, "CZ": 0.0, "PR": 0.0, "LV": 0.0, "UI": 0.0, "FN": 0.0, "ES": 0.0, "EE": 0.0, "UK": 0.0, "DU": 0.0, "FR": 0.0, "SI": 0.0, "IE": 0.0, "BE": 0.0, "LN": 0.0, "AT": 0.0, "PL": 0.0, "DE": 0.0, "SK": 0.0, "NL": 0.0, "ET": 0.0, "HU": 318525887.0, "CH": 530381760.0, "HR": 0.0, "GC": 0.0, "PT": 0.0, "RO": 0.0, "GR": 0.0}, "HU": {"BG": 0.0, "IR": 0.0, "ET": 0.0, "IT": 5969540874.0, "CZ": 0.0, "PR": 0.0, "LV": 0.0, "UI": 0.0, "FN": 0.0, "ES": 0.0, "EE": 4393267281.0, "UK": 0.0, "DU": 0.0, "FR": 0.0, "SI": 9098267625.0, "IE": 0.0, "BE": 0.0, "LN": 0.0, "AT": 0.0, "PL": 0.0, "DE": 4834926942.0, "SK": 290032170.0, "NL": 9789416009.0, "LT": 0.0, "CH": 0.0, "HR": 0.0, "GC": 0.0, "PT": 0.0, "RO": 156580670.0, "GR": 0.0}, "CH": {"LT": 0.0, "BG": 0.0, "IR": 0.0, "ET": 0.0, "CZ": 19881461798.0, "PR": 0.0, "LV": 0.0, "UI": 0.0, "FN": 0.0, "ES": 0.0, "EE": 4201155991.0, "UK": 9172443179.0, "DU": 0.0, "FR": 0.0, "SI": 0.0, "IE": 557204485.0, "BE": 0.0, "LN": 0.0, "AT": 0.0, "PL": 0.0, "DE": 0.0, "SK": 0.0, "NL": 0.0, "IT": 0.0, "HU": 0.0, "HR": 0.0, "GC": 0.0, "PT": 0.0, "RO": 0.0, "GR": 0.0}, "HR": {"LT": 8540825.0, "BG": 56487.0, "IR": 0.0, "ET": 0.0, "CZ": 0.0, "PR": 0.0, "LV": 689217.0, "UI": 0.0, "FN": 0.0, "ES": 0.0, "EE": 0.0, "UK": 0.0, "DU": 0.0, "FR": 0.0, "SI": 0.0, "IE": 0.0, "BE": 0.0, "LN": 1030390.0, "AT": 0.0, "PL": 0.0, "DE": 0.0, "SK": 0.0, "NL": 0.0, "IT": 0.0, "HU": 0.0, "CH": 0.0, "GC": 0.0, "PT": 0.0, "RO": 0.0, "GR": 0.0}, "GC": {"BG": 0.0, "IR": 11279338.0, "ET": 0.0, "IT": 859220514.0, "CZ": 0.0, "PR": 0.0, "LV": 0.0, "UI": 0.0, "FN": 0.0, "ES": 0.0, "EE": 0.0, "UK": 0.0, "DU": 0.0, "FR": 2311514814.0, "SI": 0.0, "IE": 0.0, "BE": 0.0, "LN": 0.0, "AT": 0.0, "PL": 0.0, "DE": 0.0, "SK": 0.0, "NL": 0.0, "LT": 0.0, "HU": 332810386.0, "CH": 0.0, "HR": 0.0, "PT": 0.0, "RO": 0.0, "GR": 6536690558.0}, "PT": {"BG": 0.0, "IR": 0.0, "ET": 0.0, "CZ": 0.0, "PR": 0.0, "LV": 0.0, "UI": 0.0, "FN": 0.0, "ES": 212970035.0, "EE": 0.0, "UK": 0.0, "DU": 0.0, "FR": 0.0, "SI": 0.0, "IE": 0.0, "BE": 0.0, "LN": 0.0, "AT": 0.0, "PL": 0.0, "DE": 0.0, "SK": 0.0, "NL": 0.0, "LT": 0.0, "HU": 0.0, "CH": 158150062.0, "HR": 0.0, "GC": 0.0, "IT": 0.0, "RO": 0.0, "GR": 0.0}, "RO": {"BG": 0.0, "IR": 7157133.0, "ET": 0.0, "IT": 0.0, "CZ": 17948253730.0, "PR": 0.0, "LV": 0.0, "UI": 517255831.0, "FN": 0.0, "ES": 0.0, "EE": 0.0, "UK": 0.0, "DU": 0.0, "FR": 0.0, "SI": 3556665959.0, "IE": 0.0, "BE": 0.0, "LN": 0.0, "AT": 0.0, "DE": 0.0, "SK": 1421398542.0, "NL": 0.0, "LT": 0.0, "HU": 18933027.0, "CH": 145885149.0, "HR": 0.0, "GC": 723712179.0, "PT": 0.0, "PL": 15748510.0, "GR": 0.0}, "GR": {"BG": 0.0, "IR": 0.0, "ET": 0.0, "IT": 0.0, "CZ": 0.0, "PR": 0.0, "LV": 0.0, "UI": 0.0, "FN": 0.0, "ES": 0.0, "EE": 0.0, "UK": 7315470427.0, "DU": 0.0, "FR": 0.0, "SI": 0.0, "IE": 0.0, "BE": 0.0, "LN": 0.0, "AT": 0.0, "PL": 122028111.0, "DE": 0.0, "SK": 0.0, "NL": 7287827271.0, "LT": 0.0, "HU": 0.0, "CH": 0.0, "HR": 0.0, "GC": 5896735051.0, "PT": 0.0, "RO": 0.0}}