{
    "AT": {
        "BE": 0.0,
        "BG": 0.0,
        "CH": 0.0,
        "CZ": 0.0,
        "DE": 0.0,
        "DU": 0.0,
        "EE": 0.0,
        "ES": 0.0,
        "ET": 0.0,
        "FN": 0.0,
        "FR": 0.0,
        "GC": 0.0,
        "GR": 0.0,
        "HR": 0.0,
        "HU": 3698393590.0,
        "IE": 0.0,
        "IR": 0.0,
        "IT": 0.0,
        "LN": 0.0,
        "LT": 0.0,
        "LV": 0.0,
        "NL": 6147352426.0,
        "PL": 0.0,
        "PR": 0.0,
        "PT": 0.0,
        "RO": 614168661.0,
        "SI": 0.0,
        "SK": 0.0,
        "UI": 0.0,
        "UK": 0.0
    },
    "BE": {
        "AT": 0.0,
        "BG": 0.0,
        "CH": 0.0,
        "CZ": 0.0,
        "DE": 0.0,
        "DU": 0.0,
        "EE": 1052823.0,
        "ES": 0.0,
        "ET": 0.0,
        "FN": 0.0,
        "FR": 0.0,
        "GC": 0.0,
        "GR": 0.0,
        "HR": 0.0,
        "HU": 0.0,
        "IE": 0.0,
        "IR": 0.0,
        "IT": 0.0,
        "LN": 0.0,
        "LT": 0.0,
        "LV": 0.0,
        "NL": 0.0,
        "PL": 0.0,
        "PR": 0.0,
        "PT": 0.0,
        "RO": 0.0,
        "SI": 0.0,
        "SK": 0.0,
        "UI": 0.0,
        "UK": 0.0
    },
    "BG": {
        "AT": 0.0,
        "BE": 0.0,
        "CH": 0.0,
        "CZ": 0.0,
        "DE": 0.0,
        "DU": 0.0,
        "EE": 0.0,
        "ES": 0.0,
        "ET": 0.0,
        "FN": 0.0,
        "FR": 0.0,
        "GC": 0.0,
        "GR": 0.0,
        "HR": 0.0,
        "HU": 0.0,
        "IE": 0.0,
        "IR": 0.0,
        "IT": 0.0,
        "LN": 0.0,
        "LT": 0.0,
        "LV": 0.0,
        "NL": 0.0,
        "PL": 0.0,
        "PR": 0.0,
        "PT": 0.0,
        "RO": 0.0,
        "SI": 0.0,
        "SK": 341887773.0,
        "UI": 0.0,
        "UK": 0.0
    },
    "CH": {
        "AT": 0.0,
        "BE": 0.0,
        "BG": 0.0,
        "CZ": 0.0,
        "DE": 0.0,
        "DU": 0.0,
        "EE": 0.0,
        "ES": 0.0,
        "ET": 0.0,
        "FN": 0.0,
        "FR": 0.0,
        "GC": 0.0,
        "GR": 0.0,
        "HR": 0.0,
        "HU": 0.0,
        "IE": 0.0,
        "IR": 0.0,
        "IT": 0.0,
        "LN": 0.0,
        "LT": 0.0,
        "LV": 0.0,
        "NL": 0.0,
        "PL": 0.0,
        "PR": 0.0,
        "PT": 0.0,
        "RO": 0.0,
        "SI": 0.0,
        "SK": 0.0,
        "UI": 0.0,
        "UK": 0.0
    },
    "CZ": {
        "AT": 0.0,
        "BE": 0.0,
        "BG": 0.0,
        "CH": 55591420.0,
        "DE": 0.0,
        "DU": 0.0,
        "EE": 0.0,
        "ES": 0.0,
        "ET": 0.0,
        "FN": 0.0,
        "FR": 0.0,
        "GC": 0.0,
        "GR": 0.0,
        "HR": 0.0,
        "HU": 0.0,
        "IE": 0.0,
        "IR": 0.0,
        "IT": 0.0,
        "LN": 0.0,
        "LT": 0.0,
        "LV": 0.0,
        "NL": 0.0,
        "PL": 0.0,
        "PR": 0.0,
        "PT": 0.0,
        "RO": 0.0,
        "SI": 0.0,
        "SK": 0.0,
        "UI": 0.0,
        "UK": 0.0
    },
    "DE": {
        "AT": 0.0,
        "BE": 0.0,
        "BG": 0.0,
        "CH": 0.0,
        "CZ": 0.0,
        "DU": 0.0,
        "EE": 0.0,
        "ES": 0.0,
        "ET": 0.0,
        "FN": 0.0,
        "FR": 0.0,
        "GC": 0.0,
        "GR": 0.0,
        "HR": 0.0,
        "HU": 0.0,
        "IE": 0.0,
        "IR": 0.0,
        "IT": 0.0,
        "LN": 0.0,
        "LT": 0.0,
        "LV": 0.0,
        "NL": 1661893814.0,
        "PL": 0.0,
        "PR": 0.0,
        "PT": 0.0,
        "RO": 0.0,
        "SI": 0.0,
        "SK": 831640414.0,
        "UI": 24597292018.0,
        "UK": 0.0
    },
    "DU": {
        "AT": 0.0,
        "BE": 0.0,
        "BG": 0.0,
        "CH": 14461893778.0,
        "CZ": 0.0,
        "DE": 0.0,
        "EE": 0.0,
        "ES": 0.0,
        "ET": 0.0,
        "FN": 0.0,
        "FR": 0.0,
        "GC": 0.0,
        "GR": 0.0,
        "HR": 0.0,
        "HU": 0.0,
        "IE": 14596.0,
        "IR": 0.0,
        "IT": 0.0,
        "LN": 0.0,
        "LT": 0.0,
        "LV": 0.0,
        "NL": 0.0,
        "PL": 0.0,
        "PR": 0.0,
        "PT": 0.0,
        "RO": 0.0,
        "SI": 0.0,
        "SK": 0.0,
        "UI": 0.0,
        "UK": 0.0
    },
    "EE": {
        "AT": 0.0,
        "BE": 0.0,
        "BG": 0.0,
        "CH": 0.0,
        "CZ": 0.0,
        "DE": 0.0,
        "DU": 0.0,
        "ES": 0.0,
        "ET": 0.0,
        "FN": 0.0,
        "FR": 0.0,
        "GC": 0.0,
        "GR": 0.0,
        "HR": 0.0,
        "HU": 0.0,
        "IE": 0.0,
        "IR": 0.0,
        "IT": 0.0,
        "LN": 0.0,
        "LT": 0.0,
        "LV": 0.0,
        "NL": 0.0,
        "PL": 0.0,
        "PR": 0.0,
        "PT": 0.0,
        "RO": 0.0,
        "SI": 2299952277.0,
        "SK": 0.0,
        "UI": 0.0,
        "UK": 0.0
    },
    "ES": {
        "AT": 0.0,
        "BE": 0.0,
        "BG": 127959366.0,
        "CH": 0.0,
        "CZ": 0.0,
        "DE": 0.0,
        "DU": 0.0,
        "EE": 0.0,
        "ET": 0.0,
        "FN": 0.0,
        "FR": 0.0,
        "GC": 0.0,
        "GR": 0.0,
        "HR": 0.0,
        "HU": 0.0,
        "IE": 0.0,
        "IR": 0.0,
        "IT": 0.0,
        "LN": 0.0,
        "LT": 0.0,
        "LV": 0.0,
        "NL": 0.0,
        "PL": 0.0,
        "PR": 0.0,
        "PT": 0.0,
        "RO": 0.0,
        "SI": 2723281264.0,
        "SK": 0.0,
        "UI": 0.0,
        "UK": 0.0
    },
    "ET": {
        "AT": 0.0,
        "BE": 0.0,
        "BG": 0.0,
        "CH": 0.0,
        "CZ": 0.0,
        "DE": 0.0,
        "DU": 0.0,
        "EE": 0.0,
        "ES": 0.0,
        "FN": 0.0,
        "FR": 93027330.0,
        "GC": 0.0,
        "GR": 0.0,
        "HR": 0.0,
        "HU": 0.0,
        "IE": 0.0,
        "IR": 0.0,
        "IT": 0.0,
        "LN": 0.0,
        "LT": 0.0,
        "LV": 130061431.0,
        "NL": 0.0,
        "PL": 0.0,
        "PR": 0.0,
        "PT": 0.0,
        "RO": 0.0,
        "SI": 0.0,
        "SK": 0.0,
        "UI": 0.0,
        "UK": 0.0
    },
    "FN": {
        "AT": 0.0,
        "BE": 0.0,
        "BG": 0.0,
        "CH": 0.0,
        "CZ": 0.0,
        "DE": 0.0,
        "DU": 0.0,
        "EE": 0.0,
        "ES": 0.0,
        "ET": 0.0,
        "FR": 0.0,
        "GC": 0.0,
        "GR": 4171963837.0,
        "HR": 0.0,
        "HU": 0.0,
        "IE": 0.0,
        "IR": 0.0,
        "IT": 0.0,
        "LN": 0.0,
        "LT": 0.0,
        "LV": 0.0,
        "NL": 0.0,
        "PL": 0.0,
        "PR": 0.0,
        "PT": 0.0,
        "RO": 0.0,
        "SI": 0.0,
        "SK": 0.0,
        "UI": 0.0,
        "UK": 9508449372.0
    },
    "FR": {
        "AT": 0.0,
        "BE": 0.0,
        "BG": 0.0,
        "CH": 0.0,
        "CZ": 0.0,
        "DE": 0.0,
        "DU": 0.0,
        "EE": 0.0,
        "ES": 0.0,
        "ET": 0.0,
        "FN": 0.0,
        "GC": 0.0,
        "GR": 0.0,
        "HR": 0.0,
        "HU": 0.0,
        "IE": 0.0,
        "IR": 0.0,
        "IT": 15769175230.0,
        "LN": 1473173.0,
        "LT": 0.0,
        "LV": 0.0,
        "NL": 2502031035.0,
        "PL": 0.0,
        "PR": 0.0,
        "PT": 889844917.0,
        "RO": 0.0,
        "SI": 0.0,
        "SK": 0.0,
        "UI": 0.0,
        "UK": 0.0
    },
    "GC": {
        "AT": 0.0,
        "BE": 0.0,
        "BG": 0.0,
        "CH": 0.0,
        "CZ": 0.0,
        "DE": 0.0,
        "DU": 0.0,
        "EE": 0.0,
        "ES": 0.0,
        "ET": 0.0,
        "FN": 0.0,
        "FR": 0.0,
        "GR": 2103501526.0,
        "HR": 0.0,
        "HU": 0.0,
        "IE": 0.0,
        "IR": 0.0,
        "IT": 0.0,
        "LN": 0.0,
        "LT": 0.0,
        "LV": 0.0,
        "NL": 0.0,
        "PL": 0.0,
        "PR": 0.0,
        "PT": 0.0,
        "RO": 0.0,
        "SI": 0.0,
        "SK": 10319303.0,
        "UI": 1647277388.0,
        "UK": 0.0
    },
    "GR": {
        "AT": 0.0,
        "BE": 949415.0,
        "BG": 0.0,
        "CH": 0.0,
        "CZ": 0.0,
        "DE": 0.0,
        "DU": 0.0,
        "EE": 0.0,
        "ES": 0.0,
        "ET": 0.0,
        "FN": 0.0,
        "FR": 0.0,
        "GC": 3985711848.0,
        "HR": 0.0,
        "HU": 0.0,
        "IE": 0.0,
        "IR": 0.0,
        "IT": 0.0,
        "LN": 0.0,
        "LT": 0.0,
        "LV": 0.0,
        "NL": 0.0,
        "PL": 0.0,
        "PR": 0.0,
        "PT": 0.0,
        "RO": 0.0,
        "SI": 0.0,
        "SK": 0.0,
        "UI": 0.0,
        "UK": 5143207747.0
    },
    "HR": {
        "AT": 0.0,
        "BE": 0.0,
        "BG": 0.0,
        "CH": 0.0,
        "CZ": 0.0,
        "DE": 0.0,
        "DU": 0.0,
        "EE": 0.0,
        "ES": 0.0,
        "ET": 0.0,
        "FN": 0.0,
        "FR": 0.0,
        "GC": 0.0,
        "GR": 0.0,
        "HU": 0.0,
        "IE": 3341823.0,
        "IR": 0.0,
        "IT": 0.0,
        "LN": 0.0,
        "LT": 0.0,
        "LV": 0.0,
        "NL": 0.0,
        "PL": 0.0,
        "PR": 0.0,
        "PT": 0.0,
        "RO": 0.0,
        "SI": 0.0,
        "SK": 0.0,
        "UI": 0.0,
        "UK": 0.0
    },
    "HU": {
        "AT": 0.0,
        "BE": 0.0,
        "BG": 255861881.0,
        "CH": 0.0,
        "CZ": 7697441571.0,
        "DE": 0.0,
        "DU": 0.0,
        "EE": 0.0,
        "ES": 0.0,
        "ET": 0.0,
        "FN": 0.0,
        "FR": 0.0,
        "GC": 0.0,
        "GR": 0.0,
        "HR": 0.0,
        "IE": 0.0,
        "IR": 0.0,
        "IT": 0.0,
        "LN": 0.0,
        "LT": 0.0,
        "LV": 0.0,
        "NL": 0.0,
        "PL": 0.0,
        "PR": 0.0,
        "PT": 0.0,
        "RO": 81704112.0,
        "SI": 0.0,
        "SK": 87977644.0,
        "UI": 0.0,
        "UK": 0.0
    },
    "IE": {
        "AT": 0.0,
        "BE": 0.0,
        "BG": 0.0,
        "CH": 0.0,
        "CZ": 0.0,
        "DE": 0.0,
        "DU": 0.0,
        "EE": 813587010.0,
        "ES": 0.0,
        "ET": 0.0,
        "FN": 0.0,
        "FR": 0.0,
        "GC": 0.0,
        "GR": 0.0,
        "HR": 0.0,
        "HU": 0.0,
        "IR": 0.0,
        "IT": 0.0,
        "LN": 0.0,
        "LT": 0.0,
        "LV": 0.0,
        "NL": 0.0,
        "PL": 0.0,
        "PR": 0.0,
        "PT": 0.0,
        "RO": 0.0,
        "SI": 0.0,
        "SK": 0.0,
        "UI": 0.0,
        "UK": 0.0
    },
    "IR": {
        "AT": 0.0,
        "BE": 0.0,
        "BG": 0.0,
        "CH": 0.0,
        "CZ": 173271252.0,
        "DE": 0.0,
        "DU": 0.0,
        "EE": 0.0,
        "ES": 0.0,
        "ET": 0.0,
        "FN": 0.0,
        "FR": 0.0,
        "GC": 0.0,
        "GR": 0.0,
        "HR": 0.0,
        "HU": 0.0,
        "IE": 0.0,
        "IT": 0.0,
        "LN": 0.0,
        "LT": 0.0,
        "LV": 0.0,
        "NL": 0.0,
        "PL": 0.0,
        "PR": 0.0,
        "PT": 0.0,
        "RO": 0.0,
        "SI": 0.0,
        "SK": 0.0,
        "UI": 0.0,
        "UK": 0.0
    },
    "IT": {
        "AT": 0.0,
        "BE": 0.0,
        "BG": 0.0,
        "CH": 0.0,
        "CZ": 0.0,
        "DE": 0.0,
        "DU": 0.0,
        "EE": 3239540126.0,
        "ES": 0.0,
        "ET": 0.0,
        "FN": 0.0,
        "FR": 0.0,
        "GC": 0.0,
        "GR": 0.0,
        "HR": 0.0,
        "HU": 0.0,
        "IE": 0.0,
        "IR": 0.0,
        "LN": 0.0,
        "LT": 0.0,
        "LV": 0.0,
        "NL": 0.0,
        "PL": 0.0,
        "PR": 1070366159.0,
        "PT": 0.0,
        "RO": 0.0,
        "SI": 0.0,
        "SK": 0.0,
        "UI": 2705975460.0,
        "UK": 0.0
    },
    "LN": {
        "AT": 0.0,
        "BE": 0.0,
        "BG": 0.0,
        "CH": 0.0,
        "CZ": 0.0,
        "DE": 0.0,
        "DU": 0.0,
        "EE": 8670979.0,
        "ES": 0.0,
        "ET": 0.0,
        "FN": 0.0,
        "FR": 3689622.0,
        "GC": 0.0,
        "GR": 0.0,
        "HR": 0.0,
        "HU": 0.0,
        "IE": 0.0,
        "IR": 0.0,
        "IT": 0.0,
        "LT": 0.0,
        "LV": 0.0,
        "NL": 0.0,
        "PL": 0.0,
        "PR": 0.0,
        "PT": 0.0,
        "RO": 0.0,
        "SI": 0.0,
        "SK": 0.0,
        "UI": 0.0,
        "UK": 0.0
    },
    "LT": {
        "AT": 0.0,
        "BE": 0.0,
        "BG": 0.0,
        "CH": 0.0,
        "CZ": 0.0,
        "DE": 0.0,
        "DU": 0.0,
        "EE": 0.0,
        "ES": 0.0,
        "ET": 0.0,
        "FN": 0.0,
        "FR": 0.0,
        "GC": 288999611.0,
        "GR": 0.0,
        "HR": 0.0,
        "HU": 0.0,
        "IE": 0.0,
        "IR": 0.0,
        "IT": 0.0,
        "LN": 0.0,
        "LV": 0.0,
        "NL": 0.0,
        "PL": 0.0,
        "PR": 0.0,
        "PT": 0.0,
        "RO": 0.0,
        "SI": 0.0,
        "SK": 0.0,
        "UI": 0.0,
        "UK": 0.0
    },
    "LV": {
        "AT": 0.0,
        "BE": 0.0,
        "BG": 0.0,
        "CH": 0.0,
        "CZ": 0.0,
        "DE": 0.0,
        "DU": 0.0,
        "EE": 0.0,
        "ES": 0.0,
        "ET": 92143858.0,
        "FN": 0.0,
        "FR": 777384.0,
        "GC": 0.0,
        "GR": 0.0,
        "HR": 0.0,
        "HU": 0.0,
        "IE": 0.0,
        "IR": 0.0,
        "IT": 0.0,
        "LN": 0.0,
        "LT": 0.0,
        "NL": 0.0,
        "PL": 0.0,
        "PR": 0.0,
        "PT": 0.0,
        "RO": 0.0,
        "SI": 0.0,
        "SK": 0.0,
        "UI": 0.0,
        "UK": 0.0
    },
    "NL": {
        "AT": 0.0,
        "BE": 0.0,
        "BG": 0.0,
        "CH": 0.0,
        "CZ": 0.0,
        "DE": 0.0,
        "DU": 0.0,
        "EE": 1387879808.0,
        "ES": 13694522936.0,
        "ET": 131805510.0,
        "FN": 0.0,
        "FR": 0.0,
        "GC": 3917625972.0,
        "GR": 0.0,
        "HR": 0.0,
        "HU": 0.0,
        "IE": 0.0,
        "IR": 0.0,
        "IT": 0.0,
        "LN": 0.0,
        "LT": 0.0,
        "LV": 0.0,
        "PL": 0.0,
        "PR": 0.0,
        "PT": 0.0,
        "RO": 0.0,
        "SI": 4750871792.0,
        "SK": 0.0,
        "UI": 0.0,
        "UK": 0.0
    },
    "PL": {
        "AT": 0.0,
        "BE": 0.0,
        "BG": 0.0,
        "CH": 4121118786.0,
        "CZ": 336436885.0,
        "DE": 0.0,
        "DU": 0.0,
        "EE": 0.0,
        "ES": 0.0,
        "ET": 0.0,
        "FN": 0.0,
        "FR": 0.0,
        "GC": 0.0,
        "GR": 166713603.0,
        "HR": 0.0,
        "HU": 0.0,
        "IE": 0.0,
        "IR": 0.0,
        "IT": 0.0,
        "LN": 0.0,
        "LT": 0.0,
        "LV": 0.0,
        "NL": 0.0,
        "PR": 0.0,
        "PT": 0.0,
        "RO": 0.0,
        "SI": 0.0,
        "SK": 0.0,
        "UI": 0.0,
        "UK": 0.0
    },
    "PR": {
        "AT": 0.0,
        "BE": 0.0,
        "BG": 0.0,
        "CH": 0.0,
        "CZ": 2433697080.0,
        "DE": 0.0,
        "DU": 0.0,
        "EE": 0.0,
        "ES": 0.0,
        "ET": 0.0,
        "FN": 0.0,
        "FR": 0.0,
        "GC": 0.0,
        "GR": 0.0,
        "HR": 0.0,
        "HU": 0.0,
        "IE": 420602935.0,
        "IR": 0.0,
        "IT": 0.0,
        "LN": 0.0,
        "LT": 0.0,
        "LV": 0.0,
        "NL": 0.0,
        "PL": 0.0,
        "PT": 483251919.0,
        "RO": 0.0,
        "SI": 0.0,
        "SK": 0.0,
        "UI": 0.0,
        "UK": 0.0
    },
    "PT": {
        "AT": 0.0,
        "BE": 0.0,
        "BG": 0.0,
        "CH": 431894817.0,
        "CZ": 0.0,
        "DE": 0.0,
        "DU": 0.0,
        "EE": 26451883.0,
        "ES": 0.0,
        "ET": 0.0,
        "FN": 0.0,
        "FR": 0.0,
        "GC": 0.0,
        "GR": 0.0,
        "HR": 0.0,
        "HU": 0.0,
        "IE": 0.0,
        "IR": 0.0,
        "IT": 0.0,
        "LN": 0.0,
        "LT": 0.0,
        "LV": 0.0,
        "NL": 0.0,
        "PL": 0.0,
        "PR": 0.0,
        "RO": 0.0,
        "SI": 0.0,
        "SK": 0.0,
        "UI": 0.0,
        "UK": 0.0
    },
    "RO": {
        "AT": 0.0,
        "BE": 0.0,
        "BG": 0.0,
        "CH": 149407993.0,
        "CZ": 0.0,
        "DE": 0.0,
        "DU": 0.0,
        "EE": 0.0,
        "ES": 0.0,
        "ET": 0.0,
        "FN": 0.0,
        "FR": 0.0,
        "GC": 0.0,
        "GR": 0.0,
        "HR": 1779323.0,
        "HU": 0.0,
        "IE": 0.0,
        "IR": 0.0,
        "IT": 0.0,
        "LN": 0.0,
        "LT": 0.0,
        "LV": 0.0,
        "NL": 0.0,
        "PL": 153850297.0,
        "PR": 0.0,
        "PT": 0.0,
        "SI": 0.0,
        "SK": 298739680.0,
        "UI": 12424387825.0,
        "UK": 0.0
    },
    "SI": {
        "AT": 0.0,
        "BE": 0.0,
        "BG": 0.0,
        "CH": 3690247639.0,
        "CZ": 0.0,
        "DE": 0.0,
        "DU": 0.0,
        "EE": 0.0,
        "ES": 0.0,
        "ET": 0.0,
        "FN": 1267098826.0,
        "FR": 0.0,
        "GC": 0.0,
        "GR": 0.0,
        "HR": 0.0,
        "HU": 0.0,
        "IE": 0.0,
        "IR": 13680674.0,
        "IT": 0.0,
        "LN": 0.0,
        "LT": 0.0,
        "LV": 0.0,
        "NL": 6654885456.0,
        "PL": 0.0,
        "PR": 0.0,
        "PT": 0.0,
        "RO": 0.0,
        "SK": 0.0,
        "UI": 0.0,
        "UK": 0.0
    },
    "SK": {
        "AT": 0.0,
        "BE": 0.0,
        "BG": 0.0,
        "CH": 0.0,
        "CZ": 0.0,
        "DE": 0.0,
        "DU": 0.0,
        "EE": 0.0,
        "ES": 0.0,
        "ET": 0.0,
        "FN": 0.0,
        "FR": 1383621.0,
        "GC": 0.0,
        "GR": 0.0,
        "HR": 0.0,
        "HU": 68525461.0,
        "IE": 0.0,
        "IR": 0.0,
        "IT": 0.0,
        "LN": 0.0,
        "LT": 0.0,
        "LV": 0.0,
        "NL": 0.0,
        "PL": 0.0,
        "PR": 0.0,
        "PT": 0.0,
        "RO": 1494167027.0,
        "SI": 0.0,
        "UI": 0.0,
        "UK": 0.0
    },
    "UI": {
        "AT": 0.0,
        "BE": 0.0,
        "BG": 0.0,
        "CH": 0.0,
        "CZ": 0.0,
        "DE": 21073875513.0,
        "DU": 0.0,
        "EE": 0.0,
        "ES": 0.0,
        "ET": 0.0,
        "FN": 4960131100.0,
        "FR": 0.0,
        "GC": 4821194744.0,
        "GR": 546091285.0,
        "HR": 0.0,
        "HU": 0.0,
        "IE": 0.0,
        "IR": 0.0,
        "IT": 0.0,
        "LN": 0.0,
        "LT": 1125957905.0,
        "LV": 0.0,
        "NL": 0.0,
        "PL": 0.0,
        "PR": 0.0,
        "PT": 0.0,
        "RO": 0.0,
        "SI": 0.0,
        "SK": 0.0,
        "UK": 40237550043.0
    },
    "UK": {
        "AT": 0.0,
        "BE": 0.0,
        "BG": 0.0,
        "CH": 0.0,
        "CZ": 10217274421.0,
        "DE": 0.0,
        "DU": 5132202964.0,
        "EE": 0.0,
        "ES": 0.0,
        "ET": 0.0,
        "FN": 0.0,
        "FR": 0.0,
        "GC": 0.0,
        "GR": 0.0,
        "HR": 0.0,
        "HU": 0.0,
        "IE": 0.0,
        "IR": 0.0,
        "IT": 1169128963.0,
        "LN": 0.0,
        "LT": 0.0,
        "LV": 0.0,
        "NL": 0.0,
        "PL": 4216359579.0,
        "PR": 0.0,
        "PT": 0.0,
        "RO": 1147214865.0,
        "SI": 0.0,
        "SK": 0.0,
        "UI": 27607357988.0
    }
}