{
    "AT": {
        "BE": 0.0,
        "BG": 0.0,
        "CH": 0.0,
        "CZ": 0.0,
        "DE": 0.0,
        "DU": 0.0,
        "EE": 75245693.0,
        "ES": 1139271570.0,
        "ET": 0.0,
        "FN": 0.0,
        "FR": 11469246944.0,
        "GC": 4092461064.0,
        "GR": 0.0,
        "HR": 0.0,
        "HU": 0.0,
        "IE": 0.0,
        "IR": 0.0,
        "IT": 0.0,
        "LN": 0.0,
        "LT": 0.0,
        "LV": 0.0,
        "NL": 0.0,
        "PL": 0.0,
        "PR": 0.0,
        "PT": 0.0,
        "RO": 0.0,
        "SI": 0.0,
        "SK": 0.0,
        "UI": 0.0,
        "UK": 0.0
    },
    "BE": {
        "AT": 0.0,
        "BG": 0.0,
        "CH": 0.0,
        "CZ": 0.0,
        "DE": 0.0,
        "DU": 0.0,
        "EE": 0.0,
        "ES": 0.0,
        "ET": 0.0,
        "FN": 0.0,
        "FR": 0.0,
        "GC": 0.0,
        "GR": 0.0,
        "HR": 0.0,
        "HU": 0.0,
        "IE": 0.0,
        "IR": 0.0,
        "IT": 0.0,
        "LN": 0.0,
        "LT": 0.0,
        "LV": 0.0,
        "NL": 0.0,
        "PL": 0.0,
        "PR": 0.0,
        "PT": 0.0,
        "RO": 0.0,
        "SI": 0.0,
        "SK": 0.0,
        "UI": 0.0,
        "UK": 0.0
    },
    "BG": {
        "AT": 0.0,
        "BE": 0.0,
        "CH": 0.0,
        "CZ": 0.0,
        "DE": 0.0,
        "DU": 0.0,
        "EE": 0.0,
        "ES": 0.0,
        "ET": 0.0,
        "FN": 0.0,
        "FR": 0.0,
        "GC": 0.0,
        "GR": 0.0,
        "HR": 0.0,
        "HU": 484782073.0,
        "IE": 0.0,
        "IR": 0.0,
        "IT": 0.0,
        "LN": 0.0,
        "LT": 0.0,
        "LV": 0.0,
        "NL": 0.0,
        "PL": 0.0,
        "PR": 0.0,
        "PT": 0.0,
        "RO": 0.0,
        "SI": 0.0,
        "SK": 0.0,
        "UI": 0.0,
        "UK": 0.0
    },
    "CH": {
        "AT": 0.0,
        "BE": 0.0,
        "BG": 0.0,
        "CZ": 0.0,
        "DE": 0.0,
        "DU": 0.0,
        "EE": 0.0,
        "ES": 0.0,
        "ET": 0.0,
        "FN": 0.0,
        "FR": 0.0,
        "GC": 0.0,
        "GR": 0.0,
        "HR": 0.0,
        "HU": 0.0,
        "IE": 0.0,
        "IR": 0.0,
        "IT": 0.0,
        "LN": 0.0,
        "LT": 0.0,
        "LV": 0.0,
        "NL": 0.0,
        "PL": 0.0,
        "PR": 0.0,
        "PT": 0.0,
        "RO": 449340291.0,
        "SI": 0.0,
        "SK": 0.0,
        "UI": 0.0,
        "UK": 19743885088.0
    },
    "CZ": {
        "AT": 0.0,
        "BE": 0.0,
        "BG": 0.0,
        "CH": 0.0,
        "DE": 0.0,
        "DU": 2324806151.0,
        "EE": 0.0,
        "ES": 0.0,
        "ET": 0.0,
        "FN": 0.0,
        "FR": 0.0,
        "GC": 0.0,
        "GR": 0.0,
        "HR": 0.0,
        "HU": 0.0,
        "IE": 504476834.0,
        "IR": 0.0,
        "IT": 0.0,
        "LN": 0.0,
        "LT": 0.0,
        "LV": 0.0,
        "NL": 0.0,
        "PL": 0.0,
        "PR": 0.0,
        "PT": 718857636.0,
        "RO": 0.0,
        "SI": 0.0,
        "SK": 0.0,
        "UI": 0.0,
        "UK": 0.0
    },
    "DE": {
        "AT": 0.0,
        "BE": 0.0,
        "BG": 0.0,
        "CH": 0.0,
        "CZ": 0.0,
        "DU": 0.0,
        "EE": 0.0,
        "ES": 0.0,
        "ET": 848854.0,
        "FN": 0.0,
        "FR": 0.0,
        "GC": 0.0,
        "GR": 0.0,
        "HR": 0.0,
        "HU": 0.0,
        "IE": 0.0,
        "IR": 0.0,
        "IT": 0.0,
        "LN": 0.0,
        "LT": 0.0,
        "LV": 0.0,
        "NL": 0.0,
        "PL": 0.0,
        "PR": 0.0,
        "PT": 0.0,
        "RO": 0.0,
        "SI": 0.0,
        "SK": 0.0,
        "UI": 0.0,
        "UK": 0.0
    },
    "DU": {
        "AT": 0.0,
        "BE": 0.0,
        "BG": 0.0,
        "CH": 0.0,
        "CZ": 5125839001.0,
        "DE": 0.0,
        "EE": 0.0,
        "ES": 0.0,
        "ET": 0.0,
        "FN": 0.0,
        "FR": 0.0,
        "GC": 0.0,
        "GR": 0.0,
        "HR": 0.0,
        "HU": 0.0,
        "IE": 0.0,
        "IR": 0.0,
        "IT": 0.0,
        "LN": 1272379.0,
        "LT": 0.0,
        "LV": 0.0,
        "NL": 0.0,
        "PL": 0.0,
        "PR": 0.0,
        "PT": 0.0,
        "RO": 0.0,
        "SI": 0.0,
        "SK": 192737184.0,
        "UI": 0.0,
        "UK": 0.0
    },
    "EE": {
        "AT": 0.0,
        "BE": 0.0,
        "BG": 0.0,
        "CH": 0.0,
        "CZ": 0.0,
        "DE": 780539588.0,
        "DU": 0.0,
        "ES": 0.0,
        "ET": 0.0,
        "FN": 0.0,
        "FR": 0.0,
        "GC": 0.0,
        "GR": 0.0,
        "HR": 0.0,
        "HU": 0.0,
        "IE": 0.0,
        "IR": 0.0,
        "IT": 0.0,
        "LN": 587692.0,
        "LT": 0.0,
        "LV": 19911848.0,
        "NL": 0.0,
        "PL": 0.0,
        "PR": 0.0,
        "PT": 0.0,
        "RO": 0.0,
        "SI": 0.0,
        "SK": 0.0,
        "UI": 0.0,
        "UK": 0.0
    },
    "ES": {
        "AT": 0.0,
        "BE": 0.0,
        "BG": 0.0,
        "CH": 0.0,
        "CZ": 0.0,
        "DE": 0.0,
        "DU": 0.0,
        "EE": 0.0,
        "ET": 0.0,
        "FN": 0.0,
        "FR": 0.0,
        "GC": 0.0,
        "GR": 0.0,
        "HR": 0.0,
        "HU": 0.0,
        "IE": 0.0,
        "IR": 0.0,
        "IT": 0.0,
        "LN": 0.0,
        "LT": 0.0,
        "LV": 0.0,
        "NL": 1892477070.0,
        "PL": 526912010.0,
        "PR": 0.0,
        "PT": 0.0,
        "RO": 0.0,
        "SI": 0.0,
        "SK": 0.0,
        "UI": 0.0,
        "UK": 6127126420.0
    },
    "ET": {
        "AT": 0.0,
        "BE": 0.0,
        "BG": 0.0,
        "CH": 0.0,
        "CZ": 0.0,
        "DE": 0.0,
        "DU": 0.0,
        "EE": 0.0,
        "ES": 0.0,
        "FN": 0.0,
        "FR": 0.0,
        "GC": 0.0,
        "GR": 0.0,
        "HR": 869851.0,
        "HU": 0.0,
        "IE": 0.0,
        "IR": 0.0,
        "IT": 0.0,
        "LN": 0.0,
        "LT": 0.0,
        "LV": 0.0,
        "NL": 15152.0,
        "PL": 0.0,
        "PR": 0.0,
        "PT": 0.0,
        "RO": 0.0,
        "SI": 0.0,
        "SK": 0.0,
        "UI": 0.0,
        "UK": 0.0
    },
    "FN": {
        "AT": 0.0,
        "BE": 0.0,
        "BG": 0.0,
        "CH": 0.0,
        "CZ": 0.0,
        "DE": 0.0,
        "DU": 0.0,
        "EE": 0.0,
        "ES": 0.0,
        "ET": 0.0,
        "FR": 0.0,
        "GC": 0.0,
        "GR": 0.0,
        "HR": 0.0,
        "HU": 0.0,
        "IE": 20302407.0,
        "IR": 0.0,
        "IT": 0.0,
        "LN": 0.0,
        "LT": 0.0,
        "LV": 0.0,
        "NL": 13979105004.0,
        "PL": 0.0,
        "PR": 0.0,
        "PT": 0.0,
        "RO": 0.0,
        "SI": 0.0,
        "SK": 481337501.0,
        "UI": 0.0,
        "UK": 0.0
    },
    "FR": {
        "AT": 0.0,
        "BE": 0.0,
        "BG": 0.0,
        "CH": 0.0,
        "CZ": 0.0,
        "DE": 0.0,
        "DU": 2140832360.0,
        "EE": 0.0,
        "ES": 0.0,
        "ET": 0.0,
        "FN": 0.0,
        "GC": 0.0,
        "GR": 0.0,
        "HR": 0.0,
        "HU": 0.0,
        "IE": 0.0,
        "IR": 0.0,
        "IT": 6464351647.0,
        "LN": 0.0,
        "LT": 0.0,
        "LV": 0.0,
        "NL": 0.0,
        "PL": 0.0,
        "PR": 0.0,
        "PT": 0.0,
        "RO": 0.0,
        "SI": 0.0,
        "SK": 0.0,
        "UI": 0.0,
        "UK": 0.0
    },
    "GC": {
        "AT": 0.0,
        "BE": 0.0,
        "BG": 83441132.0,
        "CH": 0.0,
        "CZ": 0.0,
        "DE": 0.0,
        "DU": 0.0,
        "EE": 0.0,
        "ES": 0.0,
        "ET": 0.0,
        "FN": 0.0,
        "FR": 0.0,
        "GR": 2445188870.0,
        "HR": 0.0,
        "HU": 0.0,
        "IE": 596510646.0,
        "IR": 0.0,
        "IT": 0.0,
        "LN": 0.0,
        "LT": 0.0,
        "LV": 0.0,
        "NL": 0.0,
        "PL": 0.0,
        "PR": 0.0,
        "PT": 0.0,
        "RO": 0.0,
        "SI": 0.0,
        "SK": 0.0,
        "UI": 0.0,
        "UK": 0.0
    },
    "GR": {
        "AT": 0.0,
        "BE": 0.0,
        "BG": 0.0,
        "CH": 0.0,
        "CZ": 0.0,
        "DE": 0.0,
        "DU": 0.0,
        "EE": 0.0,
        "ES": 0.0,
        "ET": 0.0,
        "FN": 0.0,
        "FR": 0.0,
        "GC": 4471143736.0,
        "HR": 0.0,
        "HU": 990065536.0,
        "IE": 0.0,
        "IR": 0.0,
        "IT": 0.0,
        "LN": 0.0,
        "LT": 0.0,
        "LV": 0.0,
        "NL": 0.0,
        "PL": 0.0,
        "PR": 512863939.0,
        "PT": 0.0,
        "RO": 0.0,
        "SI": 3839376949.0,
        "SK": 0.0,
        "UI": 0.0,
        "UK": 0.0
    },
    "HR": {
        "AT": 0.0,
        "BE": 0.0,
        "BG": 0.0,
        "CH": 0.0,
        "CZ": 0.0,
        "DE": 0.0,
        "DU": 0.0,
        "EE": 0.0,
        "ES": 1612720.0,
        "ET": 0.0,
        "FN": 0.0,
        "FR": 0.0,
        "GC": 0.0,
        "GR": 0.0,
        "HU": 0.0,
        "IE": 0.0,
        "IR": 0.0,
        "IT": 0.0,
        "LN": 0.0,
        "LT": 0.0,
        "LV": 0.0,
        "NL": 0.0,
        "PL": 0.0,
        "PR": 0.0,
        "PT": 0.0,
        "RO": 0.0,
        "SI": 0.0,
        "SK": 0.0,
        "UI": 0.0,
        "UK": 0.0
    },
    "HU": {
        "AT": 0.0,
        "BE": 0.0,
        "BG": 0.0,
        "CH": 0.0,
        "CZ": 0.0,
        "DE": 0.0,
        "DU": 0.0,
        "EE": 0.0,
        "ES": 0.0,
        "ET": 0.0,
        "FN": 0.0,
        "FR": 0.0,
        "GC": 0.0,
        "GR": 0.0,
        "HR": 0.0,
        "IE": 0.0,
        "IR": 0.0,
        "IT": 0.0,
        "LN": 0.0,
        "LT": 0.0,
        "LV": 0.0,
        "NL": 5426703780.0,
        "PL": 0.0,
        "PR": 0.0,
        "PT": 0.0,
        "RO": 46453761.0,
        "SI": 0.0,
        "SK": 9340980.0,
        "UI": 0.0,
        "UK": 0.0
    },
    "IE": {
        "AT": 0.0,
        "BE": 0.0,
        "BG": 0.0,
        "CH": 0.0,
        "CZ": 0.0,
        "DE": 0.0,
        "DU": 0.0,
        "EE": 0.0,
        "ES": 1077298855.0,
        "ET": 0.0,
        "FN": 0.0,
        "FR": 0.0,
        "GC": 0.0,
        "GR": 0.0,
        "HR": 0.0,
        "HU": 0.0,
        "IR": 0.0,
        "IT": 0.0,
        "LN": 0.0,
        "LT": 198086695.0,
        "LV": 0.0,
        "NL": 0.0,
        "PL": 862853637.0,
        "PR": 0.0,
        "PT": 0.0,
        "RO": 1218542563.0,
        "SI": 0.0,
        "SK": 0.0,
        "UI": 0.0,
        "UK": 0.0
    },
    "IR": {
        "AT": 0.0,
        "BE": 0.0,
        "BG": 0.0,
        "CH": 0.0,
        "CZ": 0.0,
        "DE": 0.0,
        "DU": 0.0,
        "EE": 0.0,
        "ES": 0.0,
        "ET": 0.0,
        "FN": 0.0,
        "FR": 0.0,
        "GC": 0.0,
        "GR": 0.0,
        "HR": 0.0,
        "HU": 0.0,
        "IE": 0.0,
        "IT": 0.0,
        "LN": 0.0,
        "LT": 0.0,
        "LV": 0.0,
        "NL": 0.0,
        "PL": 149960828.0,
        "PR": 0.0,
        "PT": 0.0,
        "RO": 0.0,
        "SI": 0.0,
        "SK": 0.0,
        "UI": 0.0,
        "UK": 0.0
    },
    "IT": {
        "AT": 0.0,
        "BE": 0.0,
        "BG": 0.0,
        "CH": 0.0,
        "CZ": 0.0,
        "DE": 0.0,
        "DU": 0.0,
        "EE": 0.0,
        "ES": 0.0,
        "ET": 0.0,
        "FN": 0.0,
        "FR": 0.0,
        "GC": 0.0,
        "GR": 0.0,
        "HR": 0.0,
        "HU": 0.0,
        "IE": 0.0,
        "IR": 0.0,
        "LN": 0.0,
        "LT": 0.0,
        "LV": 0.0,
        "NL": 0.0,
        "PL": 0.0,
        "PR": 0.0,
        "PT": 0.0,
        "RO": 0.0,
        "SI": 0.0,
        "SK": 0.0,
        "UI": 0.0,
        "UK": 0.0
    },
    "LN": {
        "AT": 0.0,
        "BE": 0.0,
        "BG": 0.0,
        "CH": 0.0,
        "CZ": 0.0,
        "DE": 0.0,
        "DU": 0.0,
        "EE": 1859775.0,
        "ES": 0.0,
        "ET": 0.0,
        "FN": 0.0,
        "FR": 0.0,
        "GC": 0.0,
        "GR": 0.0,
        "HR": 0.0,
        "HU": 0.0,
        "IE": 0.0,
        "IR": 0.0,
        "IT": 0.0,
        "LT": 0.0,
        "LV": 0.0,
        "NL": 0.0,
        "PL": 0.0,
        "PR": 0.0,
        "PT": 0.0,
        "RO": 1321240.0,
        "SI": 0.0,
        "SK": 0.0,
        "UI": 0.0,
        "UK": 0.0
    },
    "LT": {
        "AT": 0.0,
        "BE": 0.0,
        "BG": 0.0,
        "CH": 0.0,
        "CZ": 0.0,
        "DE": 0.0,
        "DU": 0.0,
        "EE": 0.0,
        "ES": 0.0,
        "ET": 0.0,
        "FN": 0.0,
        "FR": 0.0,
        "GC": 0.0,
        "GR": 0.0,
        "HR": 0.0,
        "HU": 0.0,
        "IE": 0.0,
        "IR": 8921257.0,
        "IT": 0.0,
        "LN": 0.0,
        "LV": 0.0,
        "NL": 0.0,
        "PL": 0.0,
        "PR": 0.0,
        "PT": 0.0,
        "RO": 0.0,
        "SI": 0.0,
        "SK": 0.0,
        "UI": 0.0,
        "UK": 335256966.0
    },
    "LV": {
        "AT": 0.0,
        "BE": 0.0,
        "BG": 0.0,
        "CH": 0.0,
        "CZ": 0.0,
        "DE": 0.0,
        "DU": 0.0,
        "EE": 7937717.0,
        "ES": 0.0,
        "ET": 0.0,
        "FN": 0.0,
        "FR": 0.0,
        "GC": 0.0,
        "GR": 0.0,
        "HR": 0.0,
        "HU": 0.0,
        "IE": 0.0,
        "IR": 0.0,
        "IT": 0.0,
        "LN": 0.0,
        "LT": 0.0,
        "NL": 0.0,
        "PL": 0.0,
        "PR": 0.0,
        "PT": 0.0,
        "RO": 0.0,
        "SI": 0.0,
        "SK": 0.0,
        "UI": 0.0,
        "UK": 0.0
    },
    "NL": {
        "AT": 0.0,
        "BE": 0.0,
        "BG": 0.0,
        "CH": 0.0,
        "CZ": 9261594623.0,
        "DE": 0.0,
        "DU": 6040550829.0,
        "EE": 0.0,
        "ES": 5626337812.0,
        "ET": 0.0,
        "FN": 0.0,
        "FR": 17685323599.0,
        "GC": 1535271580.0,
        "GR": 0.0,
        "HR": 0.0,
        "HU": 0.0,
        "IE": 0.0,
        "IR": 0.0,
        "IT": 19544413099.0,
        "LN": 0.0,
        "LT": 0.0,
        "LV": 0.0,
        "PL": 0.0,
        "PR": 518041194.0,
        "PT": 0.0,
        "RO": 0.0,
        "SI": 0.0,
        "SK": 0.0,
        "UI": 0.0,
        "UK": 0.0
    },
    "PL": {
        "AT": 0.0,
        "BE": 0.0,
        "BG": 0.0,
        "CH": 0.0,
        "CZ": 0.0,
        "DE": 3465855317.0,
        "DU": 0.0,
        "EE": 0.0,
        "ES": 0.0,
        "ET": 0.0,
        "FN": 0.0,
        "FR": 0.0,
        "GC": 0.0,
        "GR": 0.0,
        "HR": 0.0,
        "HU": 0.0,
        "IE": 0.0,
        "IR": 0.0,
        "IT": 0.0,
        "LN": 0.0,
        "LT": 0.0,
        "LV": 0.0,
        "NL": 0.0,
        "PR": 0.0,
        "PT": 0.0,
        "RO": 81898322.0,
        "SI": 0.0,
        "SK": 0.0,
        "UI": 0.0,
        "UK": 0.0
    },
    "PR": {
        "AT": 0.0,
        "BE": 0.0,
        "BG": 63769963.0,
        "CH": 0.0,
        "CZ": 0.0,
        "DE": 0.0,
        "DU": 0.0,
        "EE": 1529288178.0,
        "ES": 0.0,
        "ET": 0.0,
        "FN": 0.0,
        "FR": 0.0,
        "GC": 0.0,
        "GR": 0.0,
        "HR": 0.0,
        "HU": 0.0,
        "IE": 267787581.0,
        "IR": 0.0,
        "IT": 0.0,
        "LN": 0.0,
        "LT": 0.0,
        "LV": 0.0,
        "NL": 0.0,
        "PL": 0.0,
        "PT": 427462791.0,
        "RO": 0.0,
        "SI": 0.0,
        "SK": 0.0,
        "UI": 0.0,
        "UK": 0.0
    },
    "PT": {
        "AT": 0.0,
        "BE": 0.0,
        "BG": 0.0,
        "CH": 0.0,
        "CZ": 0.0,
        "DE": 54564768.0,
        "DU": 0.0,
        "EE": 0.0,
        "ES": 293177159.0,
        "ET": 0.0,
        "FN": 0.0,
        "FR": 0.0,
        "GC": 0.0,
        "GR": 0.0,
        "HR": 0.0,
        "HU": 0.0,
        "IE": 0.0,
        "IR": 0.0,
        "IT": 0.0,
        "LN": 0.0,
        "LT": 0.0,
        "LV": 0.0,
        "NL": 0.0,
        "PL": 0.0,
        "PR": 0.0,
        "RO": 0.0,
        "SI": 0.0,
        "SK": 0.0,
        "UI": 0.0,
        "UK": 0.0
    },
    "RO": {
        "AT": 0.0,
        "BE": 0.0,
        "BG": 491259211.0,
        "CH": 0.0,
        "CZ": 0.0,
        "DE": 0.0,
        "DU": 0.0,
        "EE": 0.0,
        "ES": 0.0,
        "ET": 0.0,
        "FN": 0.0,
        "FR": 0.0,
        "GC": 0.0,
        "GR": 0.0,
        "HR": 0.0,
        "HU": 0.0,
        "IE": 0.0,
        "IR": 0.0,
        "IT": 0.0,
        "LN": 0.0,
        "LT": 0.0,
        "LV": 0.0,
        "NL": 0.0,
        "PL": 4324144.0,
        "PR": 0.0,
        "PT": 0.0,
        "SI": 0.0,
        "SK": 93038123.0,
        "UI": 0.0,
        "UK": 5901346129.0
    },
    "SI": {
        "AT": 0.0,
        "BE": 0.0,
        "BG": 0.0,
        "CH": 0.0,
        "CZ": 0.0,
        "DE": 0.0,
        "DU": 0.0,
        "EE": 0.0,
        "ES": 0.0,
        "ET": 0.0,
        "FN": 1129189658.0,
        "FR": 0.0,
        "GC": 0.0,
        "GR": 1157817897.0,
        "HR": 0.0,
        "HU": 0.0,
        "IE": 0.0,
        "IR": 0.0,
        "IT": 0.0,
        "LN": 0.0,
        "LT": 0.0,
        "LV": 0.0,
        "NL": 0.0,
        "PL": 0.0,
        "PR": 0.0,
        "PT": 0.0,
        "RO": 0.0,
        "SK": 0.0,
        "UI": 0.0,
        "UK": 1636405398.0
    },
    "SK": {
        "AT": 0.0,
        "BE": 0.0,
        "BG": 0.0,
        "CH": 0.0,
        "CZ": 0.0,
        "DE": 0.0,
        "DU": 0.0,
        "EE": 0.0,
        "ES": 0.0,
        "ET": 0.0,
        "FN": 0.0,
        "FR": 0.0,
        "GC": 2726885451.0,
        "GR": 0.0,
        "HR": 0.0,
        "HU": 9565937.0,
        "IE": 0.0,
        "IR": 0.0,
        "IT": 0.0,
        "LN": 0.0,
        "LT": 0.0,
        "LV": 0.0,
        "NL": 0.0,
        "PL": 0.0,
        "PR": 0.0,
        "PT": 0.0,
        "RO": 0.0,
        "SI": 0.0,
        "UI": 0.0,
        "UK": 0.0
    },
    "UI": {
        "AT": 0.0,
        "BE": 0.0,
        "BG": 0.0,
        "CH": 0.0,
        "CZ": 0.0,
        "DE": 9241589304.0,
        "DU": 0.0,
        "EE": 0.0,
        "ES": 0.0,
        "ET": 0.0,
        "FN": 4431388969.0,
        "FR": 0.0,
        "GC": 0.0,
        "GR": 3446401634.0,
        "HR": 0.0,
        "HU": 0.0,
        "IE": 0.0,
        "IR": 0.0,
        "IT": 0.0,
        "LN": 0.0,
        "LT": 0.0,
        "LV": 0.0,
        "NL": 20146702198.0,
        "PL": 0.0,
        "PR": 0.0,
        "PT": 0.0,
        "RO": 0.0,
        "SI": 0.0,
        "SK": 0.0,
        "UK": 217476731.0
    },
    "UK": {
        "AT": 0.0,
        "BE": 0.0,
        "BG": 0.0,
        "CH": 0.0,
        "CZ": 0.0,
        "DE": 0.0,
        "DU": 0.0,
        "EE": 0.0,
        "ES": 46440.0,
        "ET": 0.0,
        "FN": 0.0,
        "FR": 0.0,
        "GC": 0.0,
        "GR": 0.0,
        "HR": 639320.0,
        "HU": 0.0,
        "IE": 0.0,
        "IR": 0.0,
        "IT": 0.0,
        "LN": 0.0,
        "LT": 0.0,
        "LV": 0.0,
        "NL": 0.0,
        "PL": 0.0,
        "PR": 0.0,
        "PT": 0.0,
        "RO": 0.0,
        "SI": 0.0,
        "SK": 0.0,
        "UI": 45508236450.0
    }
}